mongodb_tool.py
setup.py
CherrypyMongoDB.egg-info/PKG-INFO
CherrypyMongoDB.egg-info/SOURCES.txt
CherrypyMongoDB.egg-info/dependency_links.txt
CherrypyMongoDB.egg-info/not-zip-safe
CherrypyMongoDB.egg-info/requires.txt
CherrypyMongoDB.egg-info/top_level.txt