Metadata-Version: 1.1
Name: CherrypyMongoDB
Version: 0.2.1
Summary: MongoDb Tool For Cherrypy
Home-page: https://github.com/pylover/cherrypy-mongodb
Author: Vahid Mardani
Author-email: vahid.mardani@gmail.com
License: UNKNOWN
Keywords: Cherrypy MongoDB Tool PyMongo
Platform: UNKNOWN
Classifier: Development Status :: 5 - Production/Stable
Classifier: License :: Freeware
Classifier: Intended Audience :: Developers
Classifier: Operating System :: OS Independent
Classifier: Programming Language :: Python :: 2.6
Classifier: Programming Language :: Python :: 2.7
Classifier: Topic :: Software Development :: Libraries
